hPyT/__init__.py
hPyT/hPyT.py
hPyT-1.4.0.dist-info/LICENSE
hPyT-1.4.0.dist-info/METADATA
hPyT-1.4.0.dist-info/WHEEL
hPyT-1.4.0.dist-info/top_level.txt
hPyT-1.4.0.dist-info/RECORD
