Metadata-Version: 2.2
Name: hPyT
Version: 1.4.0
Summary: Hack Python Titlebar - A package to manipulate windows and titlebar of GUI applications made using python.
Home-page: https://github.com/zingzy/hPyT
Author: zingzy
License: MIT
Project-URL: Documentation, https://github.com/zingzy/hPyT#readme
Project-URL: Source, https://github.com/zingzy/hPyT
Project-URL: Tracker, https://github.com/zingzy/hPyT/issues
Keywords: Tkinter wxpython pyqt pyside GUI window controls decorations hide show titlebar border color animation
Classifier: Intended Audience :: Developers
Classifier: Development Status :: 5 - Production/Stable
Classifier: Intended Audience :: Developers
Classifier: License :: OSI Approved :: MIT License
Classifier: Programming Language :: Python :: 3
Classifier: Programming Language :: Python :: 3.6
Classifier: Programming Language :: Python :: 3.7
Classifier: Programming Language :: Python :: 3.8
Classifier: Programming Language :: Python :: 3.9
Classifier: Programming Language :: Python :: 3.10
Classifier: Programming Language :: Python :: 3.11
Classifier: Programming Language :: Python :: 3.12
Classifier: Operating System :: Microsoft :: Windows
Requires-Python: >=3.6
License-File: LICENSE
Dynamic: author
Dynamic: classifier
Dynamic: description
Dynamic: description-content-type
Dynamic: home-page
Dynamic: keywords
Dynamic: license
Dynamic: project-url
Dynamic: requires-python
Dynamic: summary
